xcpcio_board_spider/__init__.py
xcpcio_board_spider/core/__init__.py
xcpcio_board_spider/core/logger.py
xcpcio_board_spider/core/logo.py
xcpcio_board_spider/core/utils.py
xcpcio_board_spider/spider/__init__.py
xcpcio_board_spider/spider/csg_cpc/__init__.py
xcpcio_board_spider/spider/csg_cpc/v1/__init__.py
xcpcio_board_spider/spider/csg_cpc/v1/csg_cpc.py
xcpcio_board_spider/spider/domjudge/__init__.py
xcpcio_board_spider/spider/domjudge/v2/__init__.py
xcpcio_board_spider/spider/domjudge/v2/domjudge.py
xcpcio_board_spider/spider/domjudge/v3/__init__.py
xcpcio_board_spider/spider/domjudge/v3/domjudge.py
xcpcio_board_spider/spider/domjudge/v4/__init__.py
xcpcio_board_spider/spider/domjudge/v4/domjudge.py
xcpcio_board_spider/spider/ghost/__init__.py
xcpcio_board_spider/spider/ghost/v1/__init__.py
xcpcio_board_spider/spider/ghost/v1/ghost.py
xcpcio_board_spider/spider/nowcoder/__init__.py
xcpcio_board_spider/spider/nowcoder/v1/__init__.py
xcpcio_board_spider/spider/nowcoder/v1/nowcoder.py
xcpcio_board_spider/spider/pta/__init__.py
xcpcio_board_spider/spider/pta/v1/__init__.py
xcpcio_board_spider/spider/pta/v1/pta.py
xcpcio_board_spider/spider/pta/v2/__init__.py
xcpcio_board_spider/spider/pta/v2/pta.py
xcpcio_board_spider/spider/zoj/__init__.py
xcpcio_board_spider/spider/zoj/v2/__init__.py
xcpcio_board_spider/spider/zoj/v2/zoj.py
xcpcio_board_spider/type/__init__.py
xcpcio_board_spider/type/constants.py
xcpcio_board_spider/type/contest.py
xcpcio_board_spider/type/submission.py
xcpcio_board_spider/type/team.py
xcpcio_board_spider/type/type.py
xcpcio_board_spider-0.0.82.dist-info/LICENSE
xcpcio_board_spider-0.0.82.dist-info/METADATA
xcpcio_board_spider-0.0.82.dist-info/WHEEL
xcpcio_board_spider-0.0.82.dist-info/RECORD
